[{"num_available": 1, "fraction": 1.0, "round": 1, "elapsed_minitues": 0.019059433333333334, "loss": 0.8768020272254944, "accuracy": 0.6833333333333333}, {"num_available": 1, "fraction": 1.0, "round": 2, "elapsed_minitues": 0.0377485, "loss": 0.7346144318580627, "accuracy": 0.7166666666666667}, {"num_available": 1, "fraction": 1.0, "round": 3, "elapsed_minitues": 0.05603748333333333, "loss": 0.6008098125457764, "accuracy": 0.8}, {"num_available": 1, "fraction": 1.0, "round": 4, "elapsed_minitues": 0.07433215, "loss": 0.48865434527397156, "accuracy": 0.8}, {"num_available": 1, "fraction": 1.0, "round": 5, "elapsed_minitues": 0.09283561666666666, "loss": 0.516087532043457, "accuracy": 0.8}, {"num_available": 1, "fraction": 1.0, "round": 6, "elapsed_minitues": 0.11120828333333334, "loss": 0.3706876039505005, "accuracy": 0.8666666666666667}, {"num_available": 1, "fraction": 1.0, "round": 7, "elapsed_minitues": 0.13229805, "loss": 0.3963741362094879, "accuracy": 0.8333333333333334}, {"num_available": 1, "fraction": 1.0, "round": 8, "elapsed_minitues": 0.15080073333333335, "loss": 0.38855549693107605, "accuracy": 0.85}, {"num_available": 1, "fraction": 1.0, "round": 9, "elapsed_minitues": 0.16924245000000002, "loss": 0.3885572552680969, "accuracy": 0.85}, {"num_available": 1, "fraction": 1.0, "round": 10, "elapsed_minitues": 0.1876515, "loss": 0.38592952489852905, "accuracy": 0.85}, {"num_available": 1, "fraction": 1.0, "round": 11, "elapsed_minitues": 0.20589126666666668, "loss": 0.389248788356781, "accuracy": 0.85}, {"num_available": 1, "fraction": 1.0, "round": 12, "elapsed_minitues": 0.22427551666666667, "loss": 0.39179527759552, "accuracy": 0.8333333333333334}, {"num_available": 1, "fraction": 1.0, "round": 13, "elapsed_minitues": 0.24259321666666667, "loss": 0.39747437834739685, "accuracy": 0.8333333333333334}, {"num_available": 1, "fraction": 1.0, "round": 14, "elapsed_minitues": 0.26088916666666667, "loss": 0.39334404468536377, "accuracy": 0.8333333333333334}, {"num_available": 1, "fraction": 1.0, "round": 15, "elapsed_minitues": 0.27924203333333336, "loss": 0.3944084048271179, "accuracy": 0.8333333333333334}, {"num_available": 1, "fraction": 1.0, "round": 16, "elapsed_minitues": 0.2998488833333333, "loss": 0.3929648995399475, "accuracy": 0.8333333333333334}, {"num_available": 1, "fraction": 1.0, "round": 17, "elapsed_minitues": 0.31835378333333336, "loss": 0.3979352116584778, "accuracy": 0.85}, {"num_available": 1, "fraction": 1.0, "round": 18, "elapsed_minitues": 0.33689213333333334, "loss": 0.3984193801879883, "accuracy": 0.8333333333333334}, {"num_available": 1, "fraction": 1.0, "round": 19, "elapsed_minitues": 0.35542725, "loss": 0.4024771451950073, "accuracy": 0.8333333333333334}, {"num_available": 1, "fraction": 1.0, "round": 20, "elapsed_minitues": 0.37383116666666666, "loss": 0.4028056561946869, "accuracy": 0.8333333333333334}, {"num_available": 1, "fraction": 1.0, "round": 21, "elapsed_minitues": 0.39218088333333334, "loss": 0.40356969833374023, "accuracy": 0.8333333333333334}, {"num_available": 1, "fraction": 1.0, "round": 22, "elapsed_minitues": 0.41064415000000004, "loss": 0.4044913351535797, "accuracy": 0.8333333333333334}, {"num_available": 1, "fraction": 1.0, "round": 23, "elapsed_minitues": 0.4290086166666667, "loss": 0.40214917063713074, "accuracy": 0.85}, {"num_available": 1, "fraction": 1.0, "round": 24, "elapsed_minitues": 0.44731515, "loss": 0.40163394808769226, "accuracy": 0.85}, {"num_available": 1, "fraction": 1.0, "round": 25, "elapsed_minitues": 0.46778331666666667, "loss": 0.4052065908908844, "accuracy": 0.8333333333333334}, {"num_available": 1, "fraction": 1.0, "round": 26, "elapsed_minitues": 0.4861841333333333, "loss": 0.4073618948459625, "accuracy": 0.8333333333333334}, {"num_available": 1, "fraction": 1.0, "round": 27, "elapsed_minitues": 0.5045214666666666, "loss": 0.4078001081943512, "accuracy": 0.8333333333333334}, {"num_available": 1, "fraction": 1.0, "round": 28, "elapsed_minitues": 0.5228221333333333, "loss": 0.40868261456489563, "accuracy": 0.8333333333333334}, {"num_available": 1, "fraction": 1.0, "round": 29, "elapsed_minitues": 0.5410211, "loss": 0.41148099303245544, "accuracy": 0.8333333333333334}, {"num_available": 1, "fraction": 1.0, "round": 30, "elapsed_minitues": 0.5593261833333333, "loss": 0.4122719466686249, "accuracy": 0.8333333333333334}, {"num_available": 1, "fraction": 1.0, "round": 31, "elapsed_minitues": 0.5775917833333334, "loss": 0.413319855928421, "accuracy": 0.8333333333333334}, {"num_available": 1, "fraction": 1.0, "round": 32, "elapsed_minitues": 0.59597255, "loss": 0.41545143723487854, "accuracy": 0.8333333333333334}, {"num_available": 1, "fraction": 1.0, "round": 33, "elapsed_minitues": 0.6143874666666667, "loss": 0.4159460663795471, "accuracy": 0.8333333333333334}, {"num_available": 1, "fraction": 1.0, "round": 34, "elapsed_minitues": 0.6356205833333333, "loss": 0.4154409170150757, "accuracy": 0.8333333333333334}, {"num_available": 1, "fraction": 1.0, "round": 35, "elapsed_minitues": 0.6539660333333334, "loss": 0.4167405664920807, "accuracy": 0.8333333333333334}, {"num_available": 1, "fraction": 1.0, "round": 36, "elapsed_minitues": 0.6723102666666667, "loss": 0.415240079164505, "accuracy": 0.8333333333333334}, {"num_available": 1, "fraction": 1.0, "round": 37, "elapsed_minitues": 0.6907087, "loss": 0.4175908863544464, "accuracy": 0.8333333333333334}, {"num_available": 1, "fraction": 1.0, "round": 38, "elapsed_minitues": 0.7089509666666667, "loss": 0.4173789322376251, "accuracy": 0.8333333333333334}, {"num_available": 1, "fraction": 1.0, "round": 39, "elapsed_minitues": 0.7272232, "loss": 0.4185524582862854, "accuracy": 0.8333333333333334}, {"num_available": 1, "fraction": 1.0, "round": 40, "elapsed_minitues": 0.7455785833333334, "loss": 0.41985023021698, "accuracy": 0.8333333333333334}, {"num_available": 1, "fraction": 1.0, "round": 41, "elapsed_minitues": 0.76401065, "loss": 0.42094147205352783, "accuracy": 0.8333333333333334}, {"num_available": 1, "fraction": 1.0, "round": 42, "elapsed_minitues": 0.7822684333333334, "loss": 0.42156779766082764, "accuracy": 0.8333333333333334}, {"num_available": 1, "fraction": 1.0, "round": 43, "elapsed_minitues": 0.8031656666666667, "loss": 0.42231714725494385, "accuracy": 0.8333333333333334}, {"num_available": 1, "fraction": 1.0, "round": 44, "elapsed_minitues": 0.82139175, "loss": 0.4221796989440918, "accuracy": 0.8333333333333334}, {"num_available": 1, "fraction": 1.0, "round": 45, "elapsed_minitues": 0.83974735, "loss": 0.42389824986457825, "accuracy": 0.8333333333333334}, {"num_available": 1, "fraction": 1.0, "round": 46, "elapsed_minitues": 0.8581764833333333, "loss": 0.4249415993690491, "accuracy": 0.8333333333333334}, {"num_available": 1, "fraction": 1.0, "round": 47, "elapsed_minitues": 0.8765198333333333, "loss": 0.42355823516845703, "accuracy": 0.8333333333333334}, {"num_available": 1, "fraction": 1.0, "round": 48, "elapsed_minitues": 0.8948714833333333, "loss": 0.4249303936958313, "accuracy": 0.8333333333333334}, {"num_available": 1, "fraction": 1.0, "round": 49, "elapsed_minitues": 0.9130992833333333, "loss": 0.4247264862060547, "accuracy": 0.8333333333333334}, {"num_available": 1, "fraction": 1.0, "round": 50, "elapsed_minitues": 0.9313321666666667, "loss": 0.4246159493923187, "accuracy": 0.8333333333333334}, {"num_available": 1, "fraction": 1.0, "round": 51, "elapsed_minitues": 0.9496163833333333, "loss": 0.4256904721260071, "accuracy": 0.8333333333333334}, {"num_available": 1, "fraction": 1.0, "round": 52, "elapsed_minitues": 0.9703546333333333, "loss": 0.42668166756629944, "accuracy": 0.8333333333333334}, {"num_available": 1, "fraction": 1.0, "round": 53, "elapsed_minitues": 0.98944775, "loss": 0.4278727173805237, "accuracy": 0.8333333333333334}, {"num_available": 1, "fraction": 1.0, "round": 54, "elapsed_minitues": 1.0078012333333333, "loss": 0.42881107330322266, "accuracy": 0.8333333333333334}, {"num_available": 1, "fraction": 1.0, "round": 55, "elapsed_minitues": 1.0262415833333334, "loss": 0.4297841787338257, "accuracy": 0.8333333333333334}, {"num_available": 1, "fraction": 1.0, "round": 56, "elapsed_minitues": 1.0447183, "loss": 0.42941510677337646, "accuracy": 0.8333333333333334}, {"num_available": 1, "fraction": 1.0, "round": 57, "elapsed_minitues": 1.0631387, "loss": 0.4301358759403229, "accuracy": 0.8333333333333334}, {"num_available": 1, "fraction": 1.0, "round": 58, "elapsed_minitues": 1.0815120666666667, "loss": 0.43054333329200745, "accuracy": 0.8333333333333334}, {"num_available": 1, "fraction": 1.0, "round": 59, "elapsed_minitues": 1.0998733666666667, "loss": 0.43138226866722107, "accuracy": 0.8333333333333334}, {"num_available": 1, "fraction": 1.0, "round": 60, "elapsed_minitues": 1.1181418, "loss": 0.4321692883968353, "accuracy": 0.8333333333333334}, {"num_available": 1, "fraction": 1.0, "round": 61, "elapsed_minitues": 1.1387532166666667, "loss": 0.43189162015914917, "accuracy": 0.8333333333333334}, {"num_available": 1, "fraction": 1.0, "round": 62, "elapsed_minitues": 1.1570503, "loss": 0.4320509731769562, "accuracy": 0.8333333333333334}, {"num_available": 1, "fraction": 1.0, "round": 63, "elapsed_minitues": 1.1753952166666666, "loss": 0.43325141072273254, "accuracy": 0.8333333333333334}, {"num_available": 1, "fraction": 1.0, "round": 64, "elapsed_minitues": 1.1936698, "loss": 0.4338666498661041, "accuracy": 0.8333333333333334}, {"num_available": 1, "fraction": 1.0, "round": 65, "elapsed_minitues": 1.2119944999999999, "loss": 0.4337482154369354, "accuracy": 0.8333333333333334}, {"num_available": 1, "fraction": 1.0, "round": 66, "elapsed_minitues": 1.2304639833333333, "loss": 0.4342699944972992, "accuracy": 0.85}, {"num_available": 1, "fraction": 1.0, "round": 67, "elapsed_minitues": 1.2487844333333333, "loss": 0.43452897667884827, "accuracy": 0.85}, {"num_available": 1, "fraction": 1.0, "round": 68, "elapsed_minitues": 1.2671593333333333, "loss": 0.4352741837501526, "accuracy": 0.85}, {"num_available": 1, "fraction": 1.0, "round": 69, "elapsed_minitues": 1.28644465, "loss": 0.43565458059310913, "accuracy": 0.85}, {"num_available": 1, "fraction": 1.0, "round": 70, "elapsed_minitues": 1.3059066833333333, "loss": 0.4367910325527191, "accuracy": 0.85}, {"num_available": 1, "fraction": 1.0, "round": 71, "elapsed_minitues": 1.3243023666666667, "loss": 0.4371914267539978, "accuracy": 0.85}, {"num_available": 1, "fraction": 1.0, "round": 72, "elapsed_minitues": 1.3426549166666668, "loss": 0.43698379397392273, "accuracy": 0.85}, {"num_available": 1, "fraction": 1.0, "round": 73, "elapsed_minitues": 1.3610965333333334, "loss": 0.43732768297195435, "accuracy": 0.85}, {"num_available": 1, "fraction": 1.0, "round": 74, "elapsed_minitues": 1.37947405, "loss": 0.43754732608795166, "accuracy": 0.85}, {"num_available": 1, "fraction": 1.0, "round": 75, "elapsed_minitues": 1.3979983999999999, "loss": 0.4381026029586792, "accuracy": 0.85}, {"num_available": 1, "fraction": 1.0, "round": 76, "elapsed_minitues": 1.4163839666666667, "loss": 0.43863338232040405, "accuracy": 0.8333333333333334}, {"num_available": 1, "fraction": 1.0, "round": 77, "elapsed_minitues": 1.4348208333333334, "loss": 0.43924716114997864, "accuracy": 0.8333333333333334}, {"num_available": 1, "fraction": 1.0, "round": 78, "elapsed_minitues": 1.4542719833333335, "loss": 0.4396101236343384, "accuracy": 0.8333333333333334}, {"num_available": 1, "fraction": 1.0, "round": 79, "elapsed_minitues": 1.4727175166666666, "loss": 0.4407065212726593, "accuracy": 0.8333333333333334}, {"num_available": 1, "fraction": 1.0, "round": 80, "elapsed_minitues": 1.4911559333333335, "loss": 0.4414242208003998, "accuracy": 0.8333333333333334}, {"num_available": 1, "fraction": 1.0, "round": 81, "elapsed_minitues": 1.5096505833333334, "loss": 0.44190680980682373, "accuracy": 0.8333333333333334}, {"num_available": 1, "fraction": 1.0, "round": 82, "elapsed_minitues": 1.5280894833333332, "loss": 0.44159749150276184, "accuracy": 0.8333333333333334}, {"num_available": 1, "fraction": 1.0, "round": 83, "elapsed_minitues": 1.5463387166666667, "loss": 0.44226422905921936, "accuracy": 0.8333333333333334}, {"num_available": 1, "fraction": 1.0, "round": 84, "elapsed_minitues": 1.5648153333333332, "loss": 0.44362008571624756, "accuracy": 0.8333333333333334}, {"num_available": 1, "fraction": 1.0, "round": 85, "elapsed_minitues": 1.583189, "loss": 0.4428739845752716, "accuracy": 0.8333333333333334}, {"num_available": 1, "fraction": 1.0, "round": 86, "elapsed_minitues": 1.6014201166666666, "loss": 0.4432985186576843, "accuracy": 0.8333333333333334}, {"num_available": 1, "fraction": 1.0, "round": 87, "elapsed_minitues": 1.6214019499999999, "loss": 0.4434608817100525, "accuracy": 0.8333333333333334}, {"num_available": 1, "fraction": 1.0, "round": 88, "elapsed_minitues": 1.6396674666666666, "loss": 0.44385287165641785, "accuracy": 0.85}, {"num_available": 1, "fraction": 1.0, "round": 89, "elapsed_minitues": 1.6581550500000002, "loss": 0.4447977840900421, "accuracy": 0.85}, {"num_available": 1, "fraction": 1.0, "round": 90, "elapsed_minitues": 1.67662365, "loss": 0.4455330967903137, "accuracy": 0.8333333333333334}, {"num_available": 1, "fraction": 1.0, "round": 91, "elapsed_minitues": 1.6950346166666668, "loss": 0.44603732228279114, "accuracy": 0.8333333333333334}, {"num_available": 1, "fraction": 1.0, "round": 92, "elapsed_minitues": 1.7133658666666667, "loss": 0.4465568959712982, "accuracy": 0.8333333333333334}, {"num_available": 1, "fraction": 1.0, "round": 93, "elapsed_minitues": 1.7317925666666667, "loss": 0.44655224680900574, "accuracy": 0.85}, {"num_available": 1, "fraction": 1.0, "round": 94, "elapsed_minitues": 1.7501934166666666, "loss": 0.4457727372646332, "accuracy": 0.85}, {"num_available": 1, "fraction": 1.0, "round": 95, "elapsed_minitues": 1.7687154999999999, "loss": 0.4459545910358429, "accuracy": 0.85}, {"num_available": 1, "fraction": 1.0, "round": 96, "elapsed_minitues": 1.7881851833333333, "loss": 0.44743582606315613, "accuracy": 0.8333333333333334}, {"num_available": 1, "fraction": 1.0, "round": 97, "elapsed_minitues": 1.8066387333333334, "loss": 0.4480675756931305, "accuracy": 0.8333333333333334}, {"num_available": 1, "fraction": 1.0, "round": 98, "elapsed_minitues": 1.82515955, "loss": 0.4479638338088989, "accuracy": 0.85}, {"num_available": 1, "fraction": 1.0, "round": 99, "elapsed_minitues": 1.8438817333333333, "loss": 0.4480411112308502, "accuracy": 0.8333333333333334}, {"num_available": 1, "fraction": 1.0, "round": 100, "elapsed_minitues": 1.8627423833333334, "loss": 0.4479914903640747, "accuracy": 0.8333333333333334}]