[{"num_available": 5, "fraction": 1.0, "round": 1, "elapsed_minitues": 0.9942484166666666, "loss": 4.796588706970215, "accuracy": 0.2015151515151515}, {"num_available": 5, "fraction": 1.0, "round": 2, "elapsed_minitues": 1.0289124333333333, "loss": 4.77784833908081, "accuracy": 0.22272727272727272}, {"num_available": 5, "fraction": 1.0, "round": 3, "elapsed_minitues": 1.0654557833333334, "loss": 4.768253898620605, "accuracy": 0.2196969696969697}, {"num_available": 5, "fraction": 1.0, "round": 4, "elapsed_minitues": 1.10204165, "loss": 4.760471534729004, "accuracy": 0.2196969696969697}, {"num_available": 5, "fraction": 1.0, "round": 5, "elapsed_minitues": 1.1367768, "loss": 4.751223087310791, "accuracy": 0.23787878787878788}, {"num_available": 5, "fraction": 1.0, "round": 6, "elapsed_minitues": 1.1722319333333333, "loss": 4.77149600982666, "accuracy": 0.2196969696969697}, {"num_available": 5, "fraction": 1.0, "round": 7, "elapsed_minitues": 1.2079335333333332, "loss": 4.745890140533447, "accuracy": 0.23787878787878788}, {"num_available": 5, "fraction": 1.0, "round": 8, "elapsed_minitues": 1.2474362666666667, "loss": 4.756519603729248, "accuracy": 0.2318181818181818}, {"num_available": 5, "fraction": 1.0, "round": 9, "elapsed_minitues": 1.28218875, "loss": 4.738353633880616, "accuracy": 0.23787878787878788}, {"num_available": 5, "fraction": 1.0, "round": 10, "elapsed_minitues": 1.31740575, "loss": 4.686285209655762, "accuracy": 0.23939393939393938}, {"num_available": 5, "fraction": 1.0, "round": 11, "elapsed_minitues": 1.3523084666666667, "loss": 4.36926498413086, "accuracy": 0.49393939393939396}, {"num_available": 5, "fraction": 1.0, "round": 12, "elapsed_minitues": 1.3867015500000002, "loss": 4.04120626449585, "accuracy": 0.5333333333333333}, {"num_available": 5, "fraction": 1.0, "round": 13, "elapsed_minitues": 1.42440455, "loss": 4.228321170806884, "accuracy": 0.4621212121212121}, {"num_available": 5, "fraction": 1.0, "round": 14, "elapsed_minitues": 1.45997135, "loss": 4.103156328201294, "accuracy": 0.5242424242424243}, {"num_available": 5, "fraction": 1.0, "round": 15, "elapsed_minitues": 1.4953692666666667, "loss": 4.054552888870239, "accuracy": 0.5424242424242425}, {"num_available": 5, "fraction": 1.0, "round": 16, "elapsed_minitues": 1.5301872833333334, "loss": 3.9021379947662354, "accuracy": 0.593939393939394}, {"num_available": 5, "fraction": 1.0, "round": 17, "elapsed_minitues": 1.56826115, "loss": 3.738717794418335, "accuracy": 0.656060606060606}, {"num_available": 5, "fraction": 1.0, "round": 18, "elapsed_minitues": 1.60307625, "loss": 3.9703283309936523, "accuracy": 0.5454545454545454}, {"num_available": 5, "fraction": 1.0, "round": 19, "elapsed_minitues": 1.63964935, "loss": 3.7423558712005613, "accuracy": 0.6621212121212121}, {"num_available": 5, "fraction": 1.0, "round": 20, "elapsed_minitues": 1.67517545, "loss": 3.686757135391235, "accuracy": 0.6909090909090909}, {"num_available": 5, "fraction": 1.0, "round": 21, "elapsed_minitues": 1.709821, "loss": 3.560201644897461, "accuracy": 0.6818181818181818}, {"num_available": 5, "fraction": 1.0, "round": 22, "elapsed_minitues": 1.7460573333333334, "loss": 3.587397813796997, "accuracy": 0.7303030303030303}, {"num_available": 5, "fraction": 1.0, "round": 23, "elapsed_minitues": 1.7814993833333332, "loss": 3.3935637950897215, "accuracy": 0.7606060606060606}, {"num_available": 5, "fraction": 1.0, "round": 24, "elapsed_minitues": 1.81725955, "loss": 3.4739613056182863, "accuracy": 0.7242424242424242}, {"num_available": 5, "fraction": 1.0, "round": 25, "elapsed_minitues": 1.8525004, "loss": 3.4411202907562255, "accuracy": 0.7363636363636363}, {"num_available": 5, "fraction": 1.0, "round": 26, "elapsed_minitues": 1.8876852833333333, "loss": 3.5573016166687013, "accuracy": 0.740909090909091}, {"num_available": 5, "fraction": 1.0, "round": 27, "elapsed_minitues": 1.9251791500000002, "loss": 3.624169921875, "accuracy": 0.7196969696969697}, {"num_available": 5, "fraction": 1.0, "round": 28, "elapsed_minitues": 1.9598595333333333, "loss": 3.3777849674224854, "accuracy": 0.7681818181818182}, {"num_available": 5, "fraction": 1.0, "round": 29, "elapsed_minitues": 1.9944033333333333, "loss": 3.413781023025513, "accuracy": 0.7696969696969697}, {"num_available": 5, "fraction": 1.0, "round": 30, "elapsed_minitues": 2.030324183333333, "loss": 3.4217903137207033, "accuracy": 0.7666666666666667}, {"num_available": 5, "fraction": 1.0, "round": 31, "elapsed_minitues": 2.0679630833333333, "loss": 3.3732862949371336, "accuracy": 0.7712121212121212}, {"num_available": 5, "fraction": 1.0, "round": 32, "elapsed_minitues": 2.1031206166666667, "loss": 3.377785873413086, "accuracy": 0.7681818181818182}, {"num_available": 5, "fraction": 1.0, "round": 33, "elapsed_minitues": 2.1379687833333336, "loss": 3.4497111320495604, "accuracy": 0.753030303030303}, {"num_available": 5, "fraction": 1.0, "round": 34, "elapsed_minitues": 2.17216935, "loss": 3.359502410888672, "accuracy": 0.7742424242424243}, {"num_available": 5, "fraction": 1.0, "round": 35, "elapsed_minitues": 2.2078718166666667, "loss": 3.3468664646148683, "accuracy": 0.7606060606060606}, {"num_available": 5, "fraction": 1.0, "round": 36, "elapsed_minitues": 2.2449445999999997, "loss": 3.3066452026367186, "accuracy": 0.7803030303030303}, {"num_available": 5, "fraction": 1.0, "round": 37, "elapsed_minitues": 2.27965595, "loss": 3.297620916366577, "accuracy": 0.7833333333333333}, {"num_available": 5, "fraction": 1.0, "round": 38, "elapsed_minitues": 2.3150411666666666, "loss": 3.3505528450012205, "accuracy": 0.7787878787878788}, {"num_available": 5, "fraction": 1.0, "round": 39, "elapsed_minitues": 2.3497600999999997, "loss": 3.4052427768707276, "accuracy": 0.7757575757575758}, {"num_available": 5, "fraction": 1.0, "round": 40, "elapsed_minitues": 2.3859276, "loss": 3.2873918533325197, "accuracy": 0.7893939393939394}, {"num_available": 5, "fraction": 1.0, "round": 41, "elapsed_minitues": 2.4237569833333334, "loss": 3.272470808029175, "accuracy": 0.796969696969697}, {"num_available": 5, "fraction": 1.0, "round": 42, "elapsed_minitues": 2.458824116666667, "loss": 3.2870996952056886, "accuracy": 0.7909090909090909}, {"num_available": 5, "fraction": 1.0, "round": 43, "elapsed_minitues": 2.4929751, "loss": 3.3108852386474608, "accuracy": 0.7772727272727272}, {"num_available": 5, "fraction": 1.0, "round": 44, "elapsed_minitues": 2.5270407333333336, "loss": 3.3669219493865965, "accuracy": 0.7606060606060606}, {"num_available": 5, "fraction": 1.0, "round": 45, "elapsed_minitues": 2.5634611, "loss": 3.4066877365112305, "accuracy": 0.7772727272727272}, {"num_available": 5, "fraction": 1.0, "round": 46, "elapsed_minitues": 2.600989783333333, "loss": 3.354051351547241, "accuracy": 0.7757575757575758}, {"num_available": 5, "fraction": 1.0, "round": 47, "elapsed_minitues": 2.6353559833333335, "loss": 3.29215612411499, "accuracy": 0.7878787878787878}, {"num_available": 5, "fraction": 1.0, "round": 48, "elapsed_minitues": 2.669834766666667, "loss": 3.4485001087188722, "accuracy": 0.7727272727272727}, {"num_available": 5, "fraction": 1.0, "round": 49, "elapsed_minitues": 2.7041750333333336, "loss": 3.3008046627044676, "accuracy": 0.7803030303030303}, {"num_available": 5, "fraction": 1.0, "round": 50, "elapsed_minitues": 2.7424476666666666, "loss": 3.417015266418457, "accuracy": 0.7727272727272727}, {"num_available": 5, "fraction": 1.0, "round": 51, "elapsed_minitues": 2.777397016666667, "loss": 3.3149056911468504, "accuracy": 0.7787878787878788}, {"num_available": 5, "fraction": 1.0, "round": 52, "elapsed_minitues": 2.81240245, "loss": 3.2944078922271727, "accuracy": 0.7848484848484848}, {"num_available": 5, "fraction": 1.0, "round": 53, "elapsed_minitues": 2.8477649, "loss": 3.502015209197998, "accuracy": 0.7318181818181818}, {"num_available": 5, "fraction": 1.0, "round": 54, "elapsed_minitues": 2.8829702000000004, "loss": 3.537129354476929, "accuracy": 0.7272727272727273}, {"num_available": 5, "fraction": 1.0, "round": 55, "elapsed_minitues": 2.9213195833333336, "loss": 3.426418352127075, "accuracy": 0.7772727272727272}, {"num_available": 5, "fraction": 1.0, "round": 56, "elapsed_minitues": 2.9568467666666667, "loss": 3.3057844638824463, "accuracy": 0.7787878787878788}, {"num_available": 5, "fraction": 1.0, "round": 57, "elapsed_minitues": 2.9920361, "loss": 3.3530951499938966, "accuracy": 0.7863636363636364}, {"num_available": 5, "fraction": 1.0, "round": 58, "elapsed_minitues": 3.026678533333333, "loss": 3.424948501586914, "accuracy": 0.7666666666666667}, {"num_available": 5, "fraction": 1.0, "round": 59, "elapsed_minitues": 3.061590166666667, "loss": 3.2993303298950196, "accuracy": 0.7803030303030303}, {"num_available": 5, "fraction": 1.0, "round": 60, "elapsed_minitues": 3.099584683333333, "loss": 3.3823702335357666, "accuracy": 0.7878787878787878}, {"num_available": 5, "fraction": 1.0, "round": 61, "elapsed_minitues": 3.1357367333333332, "loss": 3.309049463272095, "accuracy": 0.7803030303030303}, {"num_available": 5, "fraction": 1.0, "round": 62, "elapsed_minitues": 3.1704757333333333, "loss": 3.308466005325317, "accuracy": 0.7803030303030303}, {"num_available": 5, "fraction": 1.0, "round": 63, "elapsed_minitues": 3.2051057, "loss": 3.2991011142730713, "accuracy": 0.7893939393939394}, {"num_available": 5, "fraction": 1.0, "round": 64, "elapsed_minitues": 3.2428872333333336, "loss": 3.2955806255340576, "accuracy": 0.793939393939394}, {"num_available": 5, "fraction": 1.0, "round": 65, "elapsed_minitues": 3.2783219333333333, "loss": 3.280171203613281, "accuracy": 0.7909090909090909}, {"num_available": 5, "fraction": 1.0, "round": 66, "elapsed_minitues": 3.31498715, "loss": 3.282825994491577, "accuracy": 0.7909090909090909}, {"num_available": 5, "fraction": 1.0, "round": 67, "elapsed_minitues": 3.3502701999999998, "loss": 3.3402225971221924, "accuracy": 0.7863636363636364}, {"num_available": 5, "fraction": 1.0, "round": 68, "elapsed_minitues": 3.38572045, "loss": 3.282545328140259, "accuracy": 0.7909090909090909}, {"num_available": 5, "fraction": 1.0, "round": 69, "elapsed_minitues": 3.4234661500000003, "loss": 3.329703855514526, "accuracy": 0.7893939393939394}, {"num_available": 5, "fraction": 1.0, "round": 70, "elapsed_minitues": 3.4587780166666664, "loss": 3.3122039318084715, "accuracy": 0.7833333333333333}, {"num_available": 5, "fraction": 1.0, "round": 71, "elapsed_minitues": 3.494989883333333, "loss": 3.275348424911499, "accuracy": 0.793939393939394}, {"num_available": 5, "fraction": 1.0, "round": 72, "elapsed_minitues": 3.5302044833333333, "loss": 3.3017756938934326, "accuracy": 0.7833333333333333}, {"num_available": 5, "fraction": 1.0, "round": 73, "elapsed_minitues": 3.5692556666666664, "loss": 3.292166233062744, "accuracy": 0.7863636363636364}, {"num_available": 5, "fraction": 1.0, "round": 74, "elapsed_minitues": 3.6055740166666665, "loss": 3.322499322891235, "accuracy": 0.7727272727272727}, {"num_available": 5, "fraction": 1.0, "round": 75, "elapsed_minitues": 3.6408628666666667, "loss": 3.459192657470703, "accuracy": 0.7757575757575758}, {"num_available": 5, "fraction": 1.0, "round": 76, "elapsed_minitues": 3.6764375333333335, "loss": 3.2958822727203367, "accuracy": 0.7848484848484848}, {"num_available": 5, "fraction": 1.0, "round": 77, "elapsed_minitues": 3.71218635, "loss": 3.374844789505005, "accuracy": 0.7484848484848485}, {"num_available": 5, "fraction": 1.0, "round": 78, "elapsed_minitues": 3.7502524833333335, "loss": 3.454065752029419, "accuracy": 0.7772727272727272}, {"num_available": 5, "fraction": 1.0, "round": 79, "elapsed_minitues": 3.785854983333333, "loss": 3.3593923568725588, "accuracy": 0.7772727272727272}, {"num_available": 5, "fraction": 1.0, "round": 80, "elapsed_minitues": 3.8214849666666666, "loss": 3.455238914489746, "accuracy": 0.7757575757575758}, {"num_available": 5, "fraction": 1.0, "round": 81, "elapsed_minitues": 3.85725755, "loss": 3.495581102371216, "accuracy": 0.7484848484848485}, {"num_available": 5, "fraction": 1.0, "round": 82, "elapsed_minitues": 3.8935204, "loss": 3.4185594081878663, "accuracy": 0.7484848484848485}, {"num_available": 5, "fraction": 1.0, "round": 83, "elapsed_minitues": 3.9317145, "loss": 3.3371203422546385, "accuracy": 0.7878787878787878}, {"num_available": 5, "fraction": 1.0, "round": 84, "elapsed_minitues": 3.9677488833333334, "loss": 3.4921270847320556, "accuracy": 0.7727272727272727}, {"num_available": 5, "fraction": 1.0, "round": 85, "elapsed_minitues": 4.003039366666667, "loss": 3.3951691150665284, "accuracy": 0.7378787878787879}, {"num_available": 5, "fraction": 1.0, "round": 86, "elapsed_minitues": 4.039013333333333, "loss": 3.399137353897095, "accuracy": 0.7803030303030303}, {"num_available": 5, "fraction": 1.0, "round": 87, "elapsed_minitues": 4.078516716666667, "loss": 3.335206937789917, "accuracy": 0.7893939393939394}, {"num_available": 5, "fraction": 1.0, "round": 88, "elapsed_minitues": 4.114778433333333, "loss": 3.3799341201782225, "accuracy": 0.7651515151515151}, {"num_available": 5, "fraction": 1.0, "round": 89, "elapsed_minitues": 4.151653033333334, "loss": 3.7136917114257812, "accuracy": 0.65}, {"num_available": 5, "fraction": 1.0, "round": 90, "elapsed_minitues": 4.187461, "loss": 3.9270604133605955, "accuracy": 0.5727272727272728}, {"num_available": 5, "fraction": 1.0, "round": 91, "elapsed_minitues": 4.2220063833333334, "loss": 3.504279851913452, "accuracy": 0.7303030303030303}, {"num_available": 5, "fraction": 1.0, "round": 92, "elapsed_minitues": 4.261493033333333, "loss": 3.5717202186584474, "accuracy": 0.7212121212121212}, {"num_available": 5, "fraction": 1.0, "round": 93, "elapsed_minitues": 4.2979547, "loss": 3.968117046356201, "accuracy": 0.5484848484848485}, {"num_available": 5, "fraction": 1.0, "round": 94, "elapsed_minitues": 4.334503216666667, "loss": 3.8942254066467283, "accuracy": 0.5393939393939394}, {"num_available": 5, "fraction": 1.0, "round": 95, "elapsed_minitues": 4.37070395, "loss": 3.7441298961639404, "accuracy": 0.6378787878787879}, {"num_available": 5, "fraction": 1.0, "round": 96, "elapsed_minitues": 4.409651716666667, "loss": 3.4571865081787108, "accuracy": 0.7515151515151515}, {"num_available": 5, "fraction": 1.0, "round": 97, "elapsed_minitues": 4.447653366666667, "loss": 3.6232465267181397, "accuracy": 0.6075757575757575}, {"num_available": 5, "fraction": 1.0, "round": 98, "elapsed_minitues": 4.483420233333334, "loss": 3.6552422046661377, "accuracy": 0.6803030303030303}, {"num_available": 5, "fraction": 1.0, "round": 99, "elapsed_minitues": 4.5193453833333335, "loss": 3.7797132968902587, "accuracy": 0.6636363636363637}, {"num_available": 5, "fraction": 1.0, "round": 100, "elapsed_minitues": 4.555651516666667, "loss": 3.9576016426086427, "accuracy": 0.556060606060606}]